initforge-0.3.0.dist-info/licenses/LICENSE
projinit/__init__.py
projinit/__main__.py
projinit/config.py
projinit/generator.py
projinit/init.py
projinit/presets.py
projinit/validators.py
projinit/presets/__init__.py
projinit/presets/builder.py
projinit/presets/core.py
projinit/presets/finder.py
projinit/presets/store.py
projinit/templates/base/.gitignore.txt
projinit/templates/base/README.md.txt
projinit/templates/base/ci.yml.txt
projinit/templates/base/pyproject.toml.txt
projinit/templates/base/requirements.txt.txt
projinit/templates/base/requirements_dev.txt.txt
projinit/templates/base/tox.ini.txt
projinit/templates/base/tests/integration/test_int.py.txt
projinit/templates/base/tests/unit/test_unit.py.txt
initforge-0.3.0.dist-info/METADATA
initforge-0.3.0.dist-info/WHEEL
initforge-0.3.0.dist-info/entry_points.txt
initforge-0.3.0.dist-info/top_level.txt
initforge-0.3.0.dist-info/RECORD
