Metadata-Version: 2.4
Name: initforge
Version: 0.3.0
Summary: Bootstrap Python projects with auto-generated structure and README
Author: Shriful Islam
License: MIT
Project-URL: Homepage, https://github.com/Shri7ul/projinit
Keywords: project-generator,bootstrap,python,template
Classifier: Programming Language :: Python :: 3
Classifier: License :: OSI Approved :: MIT License
Classifier: Operating System :: OS Independent
Requires-Python: >=3.8
License-File: LICENSE
Requires-Dist: pyyaml
Dynamic: license-file
